[{"id":"1102043001","district_id":"1102043","name":"Muara Pea"},{"id":"1102043002","district_id":"1102043","name":"Sumber Mukti"},{"id":"1102043003","district_id":"1102043","name":"Ladang Bisik"},{"id":"1102043004","district_id":"1102043","name":"Samar Dua"},{"id":"1102043005","district_id":"1102043","name":"Butar"},{"id":"1102043007","district_id":"1102043","name":"Lapahan Buaya"},{"id":"1102043008","district_id":"1102043","name":"Lentong"},{"id":"1102043009","district_id":"1102043","name":"Danau Bungara"}]