[{"id":"1405022001","district_id":"1405022","name":"Meredan"},{"id":"1405022002","district_id":"1405022","name":"Tualang"},{"id":"1405022003","district_id":"1405022","name":"Pinang Sebatang"},{"id":"1405022013","district_id":"1405022","name":"Meredan Barat"},{"id":"1405022014","district_id":"1405022","name":"Pinang Sebatang Barat"},{"id":"1405022015","district_id":"1405022","name":"Pinang Sebatang Timur"},{"id":"1405022016","district_id":"1405022","name":"Perawang Barat"},{"id":"1405022017","district_id":"1405022","name":"Perawang"},{"id":"1405022018","district_id":"1405022","name":"Tualang Timur"}]