[{"id":"1410031001","district_id":"1410031","name":"Beting"},{"id":"1410031002","district_id":"1410031","name":"Sokop"},{"id":"1410031003","district_id":"1410031","name":"Bungur"},{"id":"1410031004","district_id":"1410031","name":"Tanjung Kedabu"},{"id":"1410031005","district_id":"1410031","name":"Telesung"},{"id":"1410031006","district_id":"1410031","name":"Tenggayun Raya"},{"id":"1410031007","district_id":"1410031","name":"Sonde"},{"id":"1410031008","district_id":"1410031","name":"Kayu Ara"},{"id":"1410031009","district_id":"1410031","name":"Tanah Merah"},{"id":"1410031010","district_id":"1410031","name":"Kedabu Rapat"},{"id":"1410031011","district_id":"1410031","name":"Sendaur"}]