[{"id":"3323010012","district_id":"3323010","name":"Caturanom"},{"id":"3323010013","district_id":"3323010","name":"Parakan Kauman"},{"id":"3323010014","district_id":"3323010","name":"Parakan Wetan"},{"id":"3323010015","district_id":"3323010","name":"Campursalam"},{"id":"3323010016","district_id":"3323010","name":"Mandisari"},{"id":"3323010017","district_id":"3323010","name":"Dangkel"},{"id":"3323010018","district_id":"3323010","name":"Ringinanom"},{"id":"3323010019","district_id":"3323010","name":"Depokharjo"},{"id":"3323010029","district_id":"3323010","name":"Watukumpul"},{"id":"3323010030","district_id":"3323010","name":"Tegalroso"},{"id":"3323010037","district_id":"3323010","name":"Glapansari"},{"id":"3323010038","district_id":"3323010","name":"Sunggingsari"},{"id":"3323010039","district_id":"3323010","name":"Wanutengah"},{"id":"3323010040","district_id":"3323010","name":"Traji"},{"id":"3323010041","district_id":"3323010","name":"Bagusan"},{"id":"3323010042","district_id":"3323010","name":"Nglondong"}]