[{"id":"3503100001","district_id":"3503100","name":"Ngadirejo"},{"id":"3503100002","district_id":"3503100","name":"Kedunglurah"},{"id":"3503100003","district_id":"3503100","name":"Bendorejo"},{"id":"3503100004","district_id":"3503100","name":"Wonocoyo"},{"id":"3503100005","district_id":"3503100","name":"Ngetal"},{"id":"3503100006","district_id":"3503100","name":"Ngadirenggo"},{"id":"3503100007","district_id":"3503100","name":"Gembleb"},{"id":"3503100008","district_id":"3503100","name":"Ngulanwetan"},{"id":"3503100009","district_id":"3503100","name":"Ngulangkulon"},{"id":"3503100010","district_id":"3503100","name":"Pogalan"}]