[{"id":"6107110039","district_id":"6107160","name":"Lengkong Bindu"},{"id":"6107160001","district_id":"6107160","name":"Natai Tebedak"},{"id":"6107160002","district_id":"6107160","name":"Jambu"},{"id":"6107160003","district_id":"6107160","name":"Nanga Mau"},{"id":"6107160004","district_id":"6107160","name":"Mentunai"},{"id":"6107160005","district_id":"6107160","name":"Tuguk"},{"id":"6107160006","district_id":"6107160","name":"Nyangkom"},{"id":"6107160007","district_id":"6107160","name":"Nanga Tikan"},{"id":"6107160008","district_id":"6107160","name":"Kerapa Sepan"},{"id":"6107160009","district_id":"6107160","name":"Pelaik"},{"id":"6107160010","district_id":"6107160","name":"Tertung Mau"},{"id":"6107160011","district_id":"6107160","name":"Pakak"},{"id":"6107160012","district_id":"6107160","name":"Melingkat"},{"id":"6107160013","district_id":"6107160","name":"Sungai Buaya"},{"id":"6107160014","district_id":"6107160","name":"Sungai Sintang"},{"id":"6107160015","district_id":"6107160","name":"Sungai Garong"},{"id":"6107160016","district_id":"6107160","name":"Paoh Desa"},{"id":"6107160017","district_id":"6107160","name":"Jaya Sakti"},{"id":"6107160018","district_id":"6107160","name":"Mekar Mandiri"},{"id":"6107160019","district_id":"6107160","name":"Landau Beringin"},{"id":"6107160020","district_id":"6107160","name":"Karya Baru"},{"id":"6107160021","district_id":"6107160","name":"Bukit Segaloh"},{"id":"6107160022","district_id":"6107160","name":"Engkerangan"},{"id":"6107160023","district_id":"6107160","name":"Lalang Inggar"},{"id":"6107160024","district_id":"6107160","name":"Linggam Permai"},{"id":"6107160025","district_id":"6107160","name":"Sungai Menuang"},{"id":"6107160026","district_id":"6107160","name":"Natai Lesung"},{"id":"6107160027","district_id":"6107160","name":"Begendang Mal"},{"id":"6107160028","district_id":"6107160","name":"Sungai Ranap"},{"id":"6107160030","district_id":"6107160","name":"Nanga Lidau"},{"id":"6107160031","district_id":"6107160","name":"Mengkirai"},{"id":"6107160032","district_id":"6107160","name":"Tanjung Keliling"},{"id":"6107160033","district_id":"6107160","name":"Buluk Jegara"},{"id":"6107160034","district_id":"6107160","name":"Buluk Panjang"},{"id":"6107160035","district_id":"6107160","name":"Tanjung Putar"},{"id":"6107160036","district_id":"6107160","name":"Sungai Emang"},{"id":"6107160037","district_id":"6107160","name":"Sungai Meraya"},{"id":"6107160038","district_id":"6107160","name":"Kempas Raya"},{"id":"6107160039","district_id":"6107160","name":"Ipoh Emang"},{"id":"6107160040","district_id":"6107160","name":"Sungai Pengga"},{"id":"6107160041","district_id":"6107160","name":"Batu Netak"},{"id":"6107160042","district_id":"6107160","name":"Neran Baya"},{"id":"6107160043","district_id":"6107160","name":"Monbai Begununk"}]