[{"id":"6206030001","district_id":"6206030","name":"Jihing"},{"id":"6206030002","district_id":"6206030","name":"Air Dua"},{"id":"6206030003","district_id":"6206030","name":"Bukit Sungkai"},{"id":"6206030004","district_id":"6206030","name":"Lupu Peruca"},{"id":"6206030005","district_id":"6206030","name":"Sekuningan Baru"},{"id":"6206030006","district_id":"6206030","name":"Balai Riam"},{"id":"6206030007","district_id":"6206030","name":"Bangun Jaya"},{"id":"6206030009","district_id":"6206030","name":"Pempaning"}]