[{"id":"1106050021","district_id":"1106050","name":"Atu Gajah Reje Guru"},{"id":"1106050019","district_id":"1106050","name":"Atu Tulu"},{"id":"1106050029","district_id":"1106050","name":"Bahgie"},{"id":"1106050007","district_id":"1106050","name":"Bebesan"},{"id":"1106050001","district_id":"1106050","name":"Blang Gele"},{"id":"1106050004","district_id":"1106050","name":"Blang Kolak I"},{"id":"1106050003","district_id":"1106050","name":"Blang Kolak II"},{"id":"1106050030","district_id":"1106050","name":"Burbiah"},{"id":"1106050033","district_id":"1106050","name":"Colo Blang Gele"},{"id":"1106050009","district_id":"1106050","name":"Daling"},{"id":"1106050027","district_id":"1106050","name":"Empus Talu"},{"id":"1106050020","district_id":"1106050","name":"Gele Lah"},{"id":"1106050034","district_id":"1106050","name":"Kala Kemili"},{"id":"1106050026","district_id":"1106050","name":"Kebet"},{"id":"1106050005","district_id":"1106050","name":"Kemili"},{"id":"1106050024","district_id":"1106050","name":"Keramat Mupakat"},{"id":"1106050011","district_id":"1106050","name":"Lelabu"},{"id":"1106050028","district_id":"1106050","name":"Lemah Burbana"},{"id":"1106050032","district_id":"1106050","name":"Mah Bengi"},{"id":"1106050008","district_id":"1106050","name":"Mongal"},{"id":"1106050025","district_id":"1106050","name":"Nunang Antara"},{"id":"1106050022","district_id":"1106050","name":"Pendere Saril"},{"id":"1106050023","district_id":"1106050","name":"Sadong Juru Mudi"},{"id":"1106050006","district_id":"1106050","name":"Simpang IV"},{"id":"1106050002","district_id":"1106050","name":"Tan Saril"},{"id":"1106050010","district_id":"1106050","name":"Tensaran"},{"id":"1106050031","district_id":"1106050","name":"Ulu Nuwih"},{"id":"1106050012","district_id":"1106050","name":"Umang"}]