[{"id":"1109080047","district_id":"1109151","name":"Teungoh"},{"id":"1109151001","district_id":"1109151","name":"Beureuleung"},{"id":"1109151002","district_id":"1109151","name":"Pangge Pilok"},{"id":"1109151003","district_id":"1109151","name":"Nicah"},{"id":"1109151004","district_id":"1109151","name":"Mesj. Memeuaneuk"},{"id":"1109151005","district_id":"1109151","name":"Sentosa"},{"id":"1109151006","district_id":"1109151","name":"Sukon"},{"id":"1109151007","district_id":"1109151","name":"Daka"},{"id":"1109151010","district_id":"1109151","name":"Mesjid Beureuleung"},{"id":"1109151012","district_id":"1109151","name":"Paya"},{"id":"1109151013","district_id":"1109151","name":"Gintong"},{"id":"1109151014","district_id":"1109151","name":"Karieng"},{"id":"1109151015","district_id":"1109151","name":"Grong-Grong"}]