[{"id":"1109200014","district_id":"1109200","name":"Benteng"},{"id":"1109200004","district_id":"1109200","name":"Blang Asan"},{"id":"1109200015","district_id":"1109200","name":"Blang Paseh"},{"id":"1109200013","district_id":"1109200","name":"Blok Bengkel"},{"id":"1109200005","district_id":"1109200","name":"Blok Sawah"},{"id":"1109200003","district_id":"1109200","name":"Kampong Asan"},{"id":"1109200007","district_id":"1109200","name":"Keramat Dalam"},{"id":"1109200008","district_id":"1109200","name":"Keramat Luar"},{"id":"1109200012","district_id":"1109200","name":"Kuala Pidie"},{"id":"1109200009","district_id":"1109200","name":"Lampoh Krueng"},{"id":"1109140027","district_id":"1109200","name":"Meunasah Peukan"},{"id":"1109200006","district_id":"1109200","name":"Pante Teungoh"},{"id":"1109200010","district_id":"1109200","name":"Pasi Peukan Baro"},{"id":"1109200011","district_id":"1109200","name":"Pasi Rawa"},{"id":"1109200001","district_id":"1109200","name":"Tanjong Krueng"}]