[{"id":"1112030012","district_id":"1112030","name":"Alue Manggota"},{"id":"1112030030","district_id":"1112030","name":"Babah Lhueng"},{"id":"1112030010","district_id":"1112030","name":"Baharu"},{"id":"1112030002","district_id":"1112030","name":"Cot Jeurat"},{"id":"1112030007","district_id":"1112030","name":"Geulumpang  Payong"},{"id":"1112030029","district_id":"1112030","name":"Gudang"},{"id":"1112030019","district_id":"1112030","name":"Guhang"},{"id":"1112030009","district_id":"1112030","name":"Keude Paya"},{"id":"1112030004","district_id":"1112030","name":"Keude Siblah"},{"id":"1112030003","district_id":"1112030","name":"Kuta Bahagia"},{"id":"1112030008","district_id":"1112030","name":"Kuta Tinggi"},{"id":"1112030027","district_id":"1112030","name":"Kuta Tuha"},{"id":"1112030011","district_id":"1112030","name":"Lam Kuta"},{"id":"1112030018","district_id":"1112030","name":"Lhung Asan"},{"id":"1112030016","district_id":"1112030","name":"Lhung Tarok"},{"id":"1112030013","district_id":"1112030","name":"Mata Ie"},{"id":"1112030006","district_id":"1112030","name":"Meudang Ara"},{"id":"1112030014","district_id":"1112030","name":"Panton Raya"},{"id":"1112030005","district_id":"1112030","name":"Pasar Blangpidie"},{"id":"1112030015","district_id":"1112030","name":"Seunaloh"}]