[{"id":"1171030001","district_id":"1171030","name":"Peunayong"},{"id":"1171030002","district_id":"1171030","name":"Laksana"},{"id":"1171030003","district_id":"1171030","name":"Keuramat"},{"id":"1171030004","district_id":"1171030","name":"Kuta Alam"},{"id":"1171030005","district_id":"1171030","name":"Beurawe"},{"id":"1171030006","district_id":"1171030","name":"Kota Baru"},{"id":"1171030007","district_id":"1171030","name":"Bandar Baru"},{"id":"1171030008","district_id":"1171030","name":"Mulia"},{"id":"1171030013","district_id":"1171030","name":"Lampulo"},{"id":"1171030014","district_id":"1171030","name":"Lamdingin"},{"id":"1171030015","district_id":"1171030","name":"Lambaro Skep"}]