[{"id":"1174020002","district_id":"1174020","name":"Paloh Batee"},{"id":"1174020003","district_id":"1174020","name":"Lhok Mon Puteh"},{"id":"1174020004","district_id":"1174020","name":"Cot Girek Kandang"},{"id":"1174020006","district_id":"1174020","name":"Blang Crum"},{"id":"1174020007","district_id":"1174020","name":"Alue Awe"},{"id":"1174020008","district_id":"1174020","name":"Cut Mamplam"},{"id":"1174020009","district_id":"1174020","name":"Meunasah  Mee"},{"id":"1174020010","district_id":"1174020","name":"Meunasah Blang"},{"id":"1174020011","district_id":"1174020","name":"Uteunkot"},{"id":"1174020012","district_id":"1174020","name":"Blang Poroh"},{"id":"1174020013","district_id":"1174020","name":"Paya Punteuet"},{"id":"1174020014","district_id":"1174020","name":"Keude Cunda"},{"id":"1174020015","district_id":"1174020","name":"Meunasah  Mesjid"},{"id":"1174020016","district_id":"1174020","name":"Mns. Panggoi"},{"id":"1174020017","district_id":"1174020","name":"Paya Bili"},{"id":"1174020018","district_id":"1174020","name":"Meunasah  Alue"}]