[{"id":"1202052006","district_id":"1202052","name":"Barbaran"},{"id":"1202052009","district_id":"1202052","name":"Barbaran Jae"},{"id":"1202052005","district_id":"1202052","name":"Batang Gadis"},{"id":"1202052010","district_id":"1202052","name":"Batang Gadis Jae"},{"id":"1202052004","district_id":"1202052","name":"Huta Baringin"},{"id":"1202052007","district_id":"1202052","name":"Huta Tonga BB"},{"id":"1202052001","district_id":"1202052","name":"Longat"},{"id":"1202052008","district_id":"1202052","name":"Runding"},{"id":"1202052003","district_id":"1202052","name":"Saba Jior"},{"id":"1202052002","district_id":"1202052","name":"Sirambas"}]