[{"id":"1203080003","district_id":"1203080","name":"Aek Natas"},{"id":"1203080005","district_id":"1203080","name":"Dolok Godang"},{"id":"1203080004","district_id":"1203080","name":"Gunung Baringin"},{"id":"1203061007","district_id":"1203080","name":"Napa"},{"id":"1203061019","district_id":"1203080","name":"Pardomuan"},{"id":"1203080010","district_id":"1203080","name":"Perkebunan Marpinggan"},{"id":"1203080015","district_id":"1203080","name":"Pintu Padang"},{"id":"1203080011","district_id":"1203080","name":"Siamporik Dolok"},{"id":"1203080013","district_id":"1203080","name":"Siamporik Lombang"},{"id":"1203080012","district_id":"1203080","name":"Sibong-bong"},{"id":"1203080009","district_id":"1203080","name":"Sihopur"},{"id":"1203080002","district_id":"1203080","name":"Sihuik-huik"},{"id":"1203061001","district_id":"1203080","name":"Simarpinggan"},{"id":"1203080016","district_id":"1203080","name":"Sinyior"},{"id":"1203080017","district_id":"1203080","name":"Situmbaga"},{"id":"1203080008","district_id":"1203080","name":"Tandihat"},{"id":"1203061014","district_id":"1203080","name":"Tapian Nauli"}]