[{"id":"1502030004","district_id":"1502030","name":"Rejo Sari"},{"id":"1502030005","district_id":"1502030","name":"Pematang Kancil"},{"id":"1502030006","district_id":"1502030","name":"Tanah Abang"},{"id":"1502030007","district_id":"1502030","name":"Empang Benao"},{"id":"1502030008","district_id":"1502030","name":"Tanjung Gedang"},{"id":"1502030009","district_id":"1502030","name":"Keroya"},{"id":"1502030010","district_id":"1502030","name":"Pauh Menang"},{"id":"1502030011","district_id":"1502030","name":"Pamenang"},{"id":"1502030017","district_id":"1502030","name":"Sialang"},{"id":"1502030018","district_id":"1502030","name":"Muara Belengo"},{"id":"1502030019","district_id":"1502030","name":"Jelatang"},{"id":"1502030020","district_id":"1502030","name":"Karang Berahi"},{"id":"1502030026","district_id":"1502030","name":"Sungai Udang"},{"id":"1502030027","district_id":"1502030","name":"Pelakar Jaya"}]