[{"id":"1604133001","district_id":"1604133","name":"Geramat"},{"id":"1604133002","district_id":"1604133","name":"Lubuk Betung"},{"id":"1604133003","district_id":"1604133","name":"Perangai"},{"id":"1604133004","district_id":"1604133","name":"Tanjung Beringin"},{"id":"1604133005","district_id":"1604133","name":"Suka Merindu"},{"id":"1604133006","district_id":"1604133","name":"Talang Akar"},{"id":"1604133007","district_id":"1604133","name":"Lubuk Pedaro"},{"id":"1604133008","district_id":"1604133","name":"Tanjung Menang"},{"id":"1604133009","district_id":"1604133","name":"Padang"}]