[{"id":"1706052004","district_id":"1706052","name":"Lalang Luas"},{"id":"1706052009","district_id":"1706052","name":"Lubuk Cabau"},{"id":"1706052006","district_id":"1706052","name":"Pondok Panjang"},{"id":"1706052001","district_id":"1706052","name":"Pondok Tengah"},{"id":"1706052005","district_id":"1706052","name":"Resno"},{"id":"1706052002","district_id":"1706052","name":"Sungai Lintang"},{"id":"1706052010","district_id":"1706052","name":"Sungai Rengas"},{"id":"1706052003","district_id":"1706052","name":"Talang Petai"},{"id":"1706052007","district_id":"1706052","name":"Talang Sakti"},{"id":"1706052008","district_id":"1706052","name":"Talang Sepakat"}]