[{"id":"1812070001","district_id":"1812070","name":"Marga Jaya"},{"id":"1812070002","district_id":"1812070","name":"Mekar Jaya"},{"id":"1812070003","district_id":"1812070","name":"Suka Jaya"},{"id":"1812070004","district_id":"1812070","name":"Mulya Jaya"},{"id":"1812070005","district_id":"1812070","name":"Wono Rejo"},{"id":"1812070006","district_id":"1812070","name":"Sumber Jaya"},{"id":"1812070007","district_id":"1812070","name":"Bangun Jaya"},{"id":"1812070009","district_id":"1812070","name":"Jaya Murni"},{"id":"1812070010","district_id":"1812070","name":"Tri Tunggal Jaya"},{"id":"1812070011","district_id":"1812070","name":"Mulya Sari"},{"id":"1812070012","district_id":"1812070","name":"Dwikora Jaya"},{"id":"1812070013","district_id":"1812070","name":"Sumber Rejeki"}]