[{"id":"1906030001","district_id":"1906030","name":"Kelubi"},{"id":"1906030002","district_id":"1906030","name":"Padang"},{"id":"1906030003","district_id":"1906030","name":"Lalang"},{"id":"1906030004","district_id":"1906030","name":"Lalang Jaya"},{"id":"1906030005","district_id":"1906030","name":"Kurnia Jaya"},{"id":"1906030006","district_id":"1906030","name":"Baru"},{"id":"1906030010","district_id":"1906030","name":"Buku Limau"},{"id":"1906030011","district_id":"1906030","name":"Bentaian Jaya"},{"id":"1906030012","district_id":"1906030","name":"Mekar Jaya"}]