[{"id":"3207150001","district_id":"3207150","name":"Handapherang"},{"id":"3207150002","district_id":"3207150","name":"Ciharalang"},{"id":"3207150003","district_id":"3207150","name":"Bojongmengger"},{"id":"3207150004","district_id":"3207150","name":"Karangkamulyan"},{"id":"3207150005","district_id":"3207150","name":"Kertabumi"},{"id":"3207150006","district_id":"3207150","name":"Cijeungjing"},{"id":"3207150007","district_id":"3207150","name":"Pamalayan"},{"id":"3207150008","district_id":"3207150","name":"Dewasari"},{"id":"3207150009","district_id":"3207150","name":"Utama"},{"id":"3207150010","district_id":"3207150","name":"Kertaharja"},{"id":"3207150011","district_id":"3207150","name":"Karanganyar"}]