[{"id":"3215130011","district_id":"3215130","name":"Cikuntul"},{"id":"3215130010","district_id":"3215130","name":"Ciparagejaya"},{"id":"3215130001","district_id":"3215130","name":"Dayeuhluhur"},{"id":"3215130008","district_id":"3215130","name":"Jayanegara"},{"id":"3215130003","district_id":"3215130","name":"Lemahduhur"},{"id":"3215130002","district_id":"3215130","name":"Lemahkarya"},{"id":"3215130005","district_id":"3215130","name":"Lemahmakmur"},{"id":"3215130004","district_id":"3215130","name":"Lemahsubur"},{"id":"3215130006","district_id":"3215130","name":"Pagadungan"},{"id":"3215130013","district_id":"3215130","name":"Pancakarya"},{"id":"3215130007","district_id":"3215130","name":"Purwajaya"},{"id":"3215130012","district_id":"3215130","name":"Sumberjaya"},{"id":"3215130014","district_id":"3215130","name":"Tanjungjaya"},{"id":"3215130009","district_id":"3215130","name":"Tempuran"}]