[{"id":"3315100001","district_id":"3315100","name":"Sambirejo"},{"id":"3315100002","district_id":"3315100","name":"Tanjungrejo"},{"id":"3315100003","district_id":"3315100","name":"Kunden"},{"id":"3315100004","district_id":"3315100","name":"Tambahrejo"},{"id":"3315100005","district_id":"3315100","name":"Kropak"},{"id":"3315100006","district_id":"3315100","name":"Kalirejo"},{"id":"3315100007","district_id":"3315100","name":"Dapurno"},{"id":"3315100008","district_id":"3315100","name":"Mojorebo"},{"id":"3315100009","district_id":"3315100","name":"Wirosari"},{"id":"3315100010","district_id":"3315100","name":"Gedangan"},{"id":"3315100011","district_id":"3315100","name":"Tambakselo"},{"id":"3315100012","district_id":"3315100","name":"Karangasem"},{"id":"3315100013","district_id":"3315100","name":"Dokoro"},{"id":"3315100014","district_id":"3315100","name":"Tegalrejo"}]