[{"id":"3323130022","district_id":"3323130","name":"Bendungan"},{"id":"3323130014","district_id":"3323130","name":"Bojong"},{"id":"3323130009","district_id":"3323130","name":"Bonjor"},{"id":"3323130007","district_id":"3323130","name":"Campurejo"},{"id":"3323130012","district_id":"3323130","name":"Donorojo"},{"id":"3323130011","district_id":"3323130","name":"Nglarangan"},{"id":"3323130010","district_id":"3323130","name":"Sigedong"},{"id":"3323130023","district_id":"3323130","name":"Simpar"},{"id":"3323130008","district_id":"3323130","name":"Tempelsari"},{"id":"3323130024","district_id":"3323130","name":"Tlogo"},{"id":"3323130013","district_id":"3323130","name":"Tretep"}]