[{"id":"3324150003","district_id":"3324150","name":"Botomulyo"},{"id":"3324150006","district_id":"3324150","name":"Cepiring"},{"id":"3324150009","district_id":"3324150","name":"Damarsari"},{"id":"3324150004","district_id":"3324150","name":"Gondang"},{"id":"3324150010","district_id":"3324150","name":"Juwiring"},{"id":"3324150011","district_id":"3324150","name":"Kaliayu"},{"id":"3324150012","district_id":"3324150","name":"Kalirandugede"},{"id":"3324150007","district_id":"3324150","name":"Karangayu"},{"id":"3324150005","district_id":"3324150","name":"Karangsuno"},{"id":"3324150014","district_id":"3324150","name":"Korowelanganyar"},{"id":"3324150013","district_id":"3324150","name":"Korowelangkulon"},{"id":"3324150015","district_id":"3324150","name":"Margorejo"},{"id":"3324150001","district_id":"3324150","name":"Pandes"},{"id":"3324150002","district_id":"3324150","name":"Podosari"},{"id":"3324150008","district_id":"3324150","name":"Sidomulyo"}]