[{"id":"3507250002","district_id":"3507250","name":"Ampeldento"},{"id":"3507250012","district_id":"3507250","name":"Asrikaton"},{"id":"3507250005","district_id":"3507250","name":"Banjarejo"},{"id":"3507250011","district_id":"3507250","name":"Bunutwetan"},{"id":"3507250004","district_id":"3507250","name":"Kedungrejo"},{"id":"3507250014","district_id":"3507250","name":"Mangliawan"},{"id":"3507250010","district_id":"3507250","name":"Pakisjajar"},{"id":"3507250009","district_id":"3507250","name":"Pakiskembar"},{"id":"3507250006","district_id":"3507250","name":"Pucangsongo"},{"id":"3507250013","district_id":"3507250","name":"Saptorenggo"},{"id":"3507250001","district_id":"3507250","name":"Sekarpuro"},{"id":"3507250007","district_id":"3507250","name":"Sukoanyar"},{"id":"3507250003","district_id":"3507250","name":"Sumberkradenan"},{"id":"3507250008","district_id":"3507250","name":"Sumberpasir"},{"id":"3507250015","district_id":"3507250","name":"Tirtomoyo"}]