[{"id":"3520130014","district_id":"3520130","name":"Bangunasri"},{"id":"3520130001","district_id":"3520130","name":"Banjarejo"},{"id":"3520130015","district_id":"3520130","name":"Blaran"},{"id":"3520130004","district_id":"3520130","name":"Bogorejo"},{"id":"3520130017","district_id":"3520130","name":"Jonggrang"},{"id":"3520130003","district_id":"3520130","name":"Karangsono"},{"id":"3520130008","district_id":"3520130","name":"Klagen"},{"id":"3520130016","district_id":"3520130","name":"Mangge"},{"id":"3520130006","district_id":"3520130","name":"Manjung"},{"id":"3520130013","district_id":"3520130","name":"Ngumpul"},{"id":"3520130007","district_id":"3520130","name":"Panggung"},{"id":"3520130002","district_id":"3520130","name":"Purwodadi"},{"id":"3520130023","district_id":"3520130","name":"Rejomulyo"},{"id":"3520130005","district_id":"3520130","name":"Tebon"}]