[{"id":"3522240005","district_id":"3522240","name":"Basah"},{"id":"3522240001","district_id":"3522240","name":"Batokan"},{"id":"3522240002","district_id":"3522240","name":"Betet"},{"id":"3522240008","district_id":"3522240","name":"Kasiman"},{"id":"3522240007","district_id":"3522240","name":"Ngaglik"},{"id":"3522240006","district_id":"3522240","name":"Sambeng"},{"id":"3522240009","district_id":"3522240","name":"Sekaran"},{"id":"3522240004","district_id":"3522240","name":"Sidomukti"},{"id":"3522240010","district_id":"3522240","name":"Tambakmerak"},{"id":"3522240003","district_id":"3522240","name":"Tembeling"}]