[{"id":"3522160015","district_id":"3522160","name":"Banjarrejo"},{"id":"3522160011","district_id":"3522160","name":"Campurejo"},{"id":"3522160001","district_id":"3522160","name":"Jetak"},{"id":"3522160008","district_id":"3522160","name":"Kadipaten"},{"id":"3522160013","district_id":"3522160","name":"Kalirejo"},{"id":"3522160010","district_id":"3522160","name":"Karang pacar"},{"id":"3522160017","district_id":"3522160","name":"Kauman"},{"id":"3522160006","district_id":"3522160","name":"Kepatihan"},{"id":"3522160005","district_id":"3522160","name":"Klangon"},{"id":"3522160018","district_id":"3522160","name":"Ledok Kulon"},{"id":"3522160016","district_id":"3522160","name":"Ledok Wetan"},{"id":"3522160007","district_id":"3522160","name":"Mojokampung"},{"id":"3522160014","district_id":"3522160","name":"Mulyoagung"},{"id":"3522160009","district_id":"3522160","name":"Ngrowo"},{"id":"3522160002","district_id":"3522160","name":"Pacul"},{"id":"3522160012","district_id":"3522160","name":"Semanding"},{"id":"3522160003","district_id":"3522160","name":"Sukorejo"},{"id":"3522160004","district_id":"3522160","name":"Sumbang"}]