[{"id":"3601070008","district_id":"3601070","name":"Cibitung"},{"id":"3601070006","district_id":"3601070","name":"Curuglanglang"},{"id":"3601070004","district_id":"3601070","name":"Gunungbatu"},{"id":"3601070018","district_id":"3601070","name":"Kotadukuh"},{"id":"3601070003","district_id":"3601070","name":"Lebak"},{"id":"3601070007","district_id":"3601070","name":"Munjul"},{"id":"3601070005","district_id":"3601070","name":"Panacaran"},{"id":"3601070019","district_id":"3601070","name":"Pasanggrahan"},{"id":"3601070020","district_id":"3601070","name":"Sukasaba"}]