[{"id":"5202070005","district_id":"5202070","name":"Barejulat"},{"id":"5202070008","district_id":"5202070","name":"Batu Tulis"},{"id":"5202070011","district_id":"5202070","name":"Bonjeruk"},{"id":"5202070006","district_id":"5202070","name":"Bunkate"},{"id":"5202070004","district_id":"5202070","name":"Gemel"},{"id":"5202070009","district_id":"5202070","name":"Jelantik"},{"id":"5202070001","district_id":"5202070","name":"Labulia"},{"id":"5202070007","district_id":"5202070","name":"Nyerot"},{"id":"5202070013","district_id":"5202070","name":"Pengenjek"},{"id":"5202070012","district_id":"5202070","name":"Perina"},{"id":"5202070003","district_id":"5202070","name":"Puyung"},{"id":"5202070002","district_id":"5202070","name":"Sukarara"},{"id":"5202070010","district_id":"5202070","name":"Ubung"}]