[{"id":"5313120004","district_id":"5313120","name":"Bulan"},{"id":"5313120005","district_id":"5313120","name":"Pong Lao"},{"id":"5313120006","district_id":"5313120","name":"Cumbi"},{"id":"5313120007","district_id":"5313120","name":"Poco Likang"},{"id":"5313120008","district_id":"5313120","name":"Pong Murung"},{"id":"5313120009","district_id":"5313120","name":"Pong Leko"},{"id":"5313120011","district_id":"5313120","name":"Belang Turi"},{"id":"5313120012","district_id":"5313120","name":"Golo Worok"},{"id":"5313120013","district_id":"5313120","name":"Meler"},{"id":"5313120014","district_id":"5313120","name":"Wae Belang"},{"id":"5313120015","district_id":"5313120","name":"Rai"},{"id":"5313120016","district_id":"5313120","name":"Benteng Kuwu"},{"id":"5313120017","district_id":"5313120","name":"Kakor"},{"id":"5313120018","district_id":"5313120","name":"Beo Rahong"},{"id":"5313120029","district_id":"5313120","name":"Bangka Lao"},{"id":"5313120030","district_id":"5313120","name":"Compang Dalo"},{"id":"5313120031","district_id":"5313120","name":"Compang Namut"},{"id":"5313120033","district_id":"5313120","name":"Bea Kakor"}]