[{"id":"5316011003","district_id":"5316011","name":"Dameka"},{"id":"5316011008","district_id":"5316011","name":"Elu"},{"id":"5316011007","district_id":"5316011","name":"Konda Maloba"},{"id":"5316011005","district_id":"5316011","name":"Malinjak"},{"id":"5316011002","district_id":"5316011","name":"Manurara"},{"id":"5316011009","district_id":"5316011","name":"Oka Wacu"},{"id":"5316011006","district_id":"5316011","name":"Tana Modu"},{"id":"5316011004","district_id":"5316011","name":"Wailawa"},{"id":"5316011001","district_id":"5316011","name":"Waimanu"}]