[{"id":"6101040019","district_id":"6101040","name":"Sungai Rambah"},{"id":"6101040020","district_id":"6101040","name":"Gapura"},{"id":"6101040021","district_id":"6101040","name":"Kartiasa"},{"id":"6101040022","district_id":"6101040","name":"Saing Rambi"},{"id":"6101040023","district_id":"6101040","name":"Lumbang"},{"id":"6101040024","district_id":"6101040","name":"Durian"},{"id":"6101040025","district_id":"6101040","name":"Pasar Melayu"},{"id":"6101040026","district_id":"6101040","name":"Pendawan"},{"id":"6101040027","district_id":"6101040","name":"Tanjung Bugis"},{"id":"6101040028","district_id":"6101040","name":"Lubuk Dagang"},{"id":"6101040029","district_id":"6101040","name":"Dalam Kaum"},{"id":"6101040030","district_id":"6101040","name":"Tanjung Mekar"},{"id":"6101040031","district_id":"6101040","name":"Tumuk Manggis"},{"id":"6101040032","district_id":"6101040","name":"Jagur"},{"id":"6101040033","district_id":"6101040","name":"Lorong"},{"id":"6101040034","district_id":"6101040","name":"Sebayan"},{"id":"6101040035","district_id":"6101040","name":"Sumber Harapan"},{"id":"6101040040","district_id":"6101040","name":"Semangau"}]