[{"id":"6202020005","district_id":"6202020","name":"Sebamban"},{"id":"6202020006","district_id":"6202020","name":"Samuda Besar"},{"id":"6202020007","district_id":"6202020","name":"Samuda Kecil"},{"id":"6202020008","district_id":"6202020","name":"Samuda Kota"},{"id":"6202020009","district_id":"6202020","name":"Basirih Hilir"},{"id":"6202020010","district_id":"6202020","name":"Jaya Kelapa"},{"id":"6202020011","district_id":"6202020","name":"Basirih Hulu"},{"id":"6202020012","district_id":"6202020","name":"Jaya Karet"},{"id":"6202020013","district_id":"6202020","name":"Sei Ijum Raya"},{"id":"6202020014","district_id":"6202020","name":"Handil Sohor"}]