[{"id":"6205060019","district_id":"6205060","name":"Bengahon"},{"id":"6205060023","district_id":"6205060","name":"Haragandang"},{"id":"6205060026","district_id":"6205060","name":"Hurung Enep"},{"id":"6205060011","district_id":"6205060","name":"Ipu"},{"id":"6205060014","district_id":"6205060","name":"Juju Baru"},{"id":"6205060022","district_id":"6205060","name":"Karendan"},{"id":"6205060013","district_id":"6205060","name":"Lahei I"},{"id":"6205060012","district_id":"6205060","name":"Lahei II"},{"id":"6205060015","district_id":"6205060","name":"Muara Bakah"},{"id":"6205060018","district_id":"6205060","name":"Muara Inu"},{"id":"6205060021","district_id":"6205060","name":"Muara Pari"},{"id":"6205060010","district_id":"6205060","name":"Mukut"},{"id":"6205060020","district_id":"6205060","name":"Rahaden"}]