[{"id":"6213020007","district_id":"6213020","name":"'Muara Ja''an'"},{"id":"6213020005","district_id":"6213020","name":"'Panu''ut'"},{"id":"6213020008","district_id":"6213020","name":"Bahitom"},{"id":"6213020003","district_id":"6213020","name":"Batu Putih"},{"id":"6213020011","district_id":"6213020","name":"Beriwit"},{"id":"6213020009","district_id":"6213020","name":"Danau Usung"},{"id":"6213020001","district_id":"6213020","name":"Dirung"},{"id":"6213020010","district_id":"6213020","name":"Juking Pajang"},{"id":"6213020002","district_id":"6213020","name":"Malasan"},{"id":"6213020004","district_id":"6213020","name":"Mangkahui"},{"id":"6213020014","district_id":"6213020","name":"Muara Bumban"},{"id":"6213020013","district_id":"6213020","name":"Muara Sumpoi"},{"id":"6213020006","district_id":"6213020","name":"Muara Untu"},{"id":"6213020015","district_id":"6213020","name":"Penyang"},{"id":"6213020012","district_id":"6213020","name":"Puruk Cahu"}]