[{"id":"7102121001","district_id":"7102121","name":"Ranolambot"},{"id":"7102121002","district_id":"7102121","name":"Tombasian Atas"},{"id":"7102121003","district_id":"7102121","name":"Kanonang Dua"},{"id":"7102121004","district_id":"7102121","name":"Kanonang Empat"},{"id":"7102121005","district_id":"7102121","name":"Kanonang Lima"},{"id":"7102121006","district_id":"7102121","name":"Kanonang Satu"},{"id":"7102121007","district_id":"7102121","name":"Tombasian Atas Satu"},{"id":"7102121008","district_id":"7102121","name":"Tombasian Bawah"},{"id":"7102121009","district_id":"7102121","name":"Kayuuwi Satu"},{"id":"7102121010","district_id":"7102121","name":"Kayuuwi"}]