[{"id":"7322040009","district_id":"7322040","name":"Tolangi"},{"id":"7322040013","district_id":"7322040","name":"Sukadamai"},{"id":"7322040014","district_id":"7322040","name":"Mulyasari"},{"id":"7322040015","district_id":"7322040","name":"Wonosari"},{"id":"7322040016","district_id":"7322040","name":"Sukamaju"},{"id":"7322040017","district_id":"7322040","name":"Salulemo"},{"id":"7322040018","district_id":"7322040","name":"Saptamarga"},{"id":"7322040019","district_id":"7322040","name":"Kaluku"},{"id":"7322040020","district_id":"7322040","name":"Tulungsari"},{"id":"7322040021","district_id":"7322040","name":"Katulungan"},{"id":"7322040022","district_id":"7322040","name":"Tulung Indah"},{"id":"7322040023","district_id":"7322040","name":"Tamboke"},{"id":"7322040024","district_id":"7322040","name":"Minanga Tallu"},{"id":"7322040025","district_id":"7322040","name":"Lampuawa"}]