[{"id":"7403141002","district_id":"7403141","name":"Anggoro"},{"id":"7403141003","district_id":"7403141","name":"Bendewuta"},{"id":"7403141001","district_id":"7403141","name":"Dawi-dawi"},{"id":"7403141006","district_id":"7403141","name":"Duriaasi"},{"id":"7403141016","district_id":"7403141","name":"Lalohao"},{"id":"7403141021","district_id":"7403141","name":"Lalousu"},{"id":"7403141029","district_id":"7403141","name":"Langgonawe"},{"id":"7403141025","district_id":"7403141","name":"Polandangi"},{"id":"7403141005","district_id":"7403141","name":"Puuduria"},{"id":"7403141026","district_id":"7403141","name":"Tawarolondo"},{"id":"7403141022","district_id":"7403141","name":"Tetemotaha"},{"id":"7402192029","district_id":"7403141","name":"Tetewonua"},{"id":"7402192020","district_id":"7403141","name":"Tomulipu \/ Wakusao"},{"id":"7403141015","district_id":"7403141","name":"Wawonggole"},{"id":"7403141017","district_id":"7403141","name":"Wawoone"},{"id":"7403141004","district_id":"7403141","name":"Wawosolo"}]