[{"id":"7505031001","district_id":"7505031","name":"Dunu"},{"id":"7505031002","district_id":"7505031","name":"Monano"},{"id":"7505031003","district_id":"7505031","name":"Tudi"},{"id":"7505031004","district_id":"7505031","name":"Monas"},{"id":"7505031005","district_id":"7505031","name":"Tolitehuyu"},{"id":"7505031006","district_id":"7505031","name":"Zuriyati"},{"id":"7505031007","district_id":"7505031","name":"Mokonowu"},{"id":"7505031008","district_id":"7505031","name":"Pilohulata"},{"id":"7505031009","district_id":"7505031","name":"Garapia"},{"id":"7505031010","district_id":"7505031","name":"Sogu"}]