[{"id":"7601011001","district_id":"7601011","name":"Baurung"},{"id":"7601011002","district_id":"7601011","name":"Labuang"},{"id":"7601011003","district_id":"7601011","name":"Tande"},{"id":"7601011004","district_id":"7601011","name":"Baruga"},{"id":"7601011005","district_id":"7601011","name":"Baruga Dhua"},{"id":"7601011006","district_id":"7601011","name":"Lembang"},{"id":"7601011007","district_id":"7601011","name":"Labuang Utara"},{"id":"7601011008","district_id":"7601011","name":"Tande Timur"},{"id":"7601011009","district_id":"7601011","name":"Buttu Baruga"}]