[{"id":"1503010","regency_id":"1503","name":"Batang Asai"},{"id":"1503020","regency_id":"1503","name":"Limun"},{"id":"1503021","regency_id":"1503","name":"Cermin Nan Gedang"},{"id":"1503030","regency_id":"1503","name":"Pelawan"},{"id":"1503031","regency_id":"1503","name":"Singkut"},{"id":"1503040","regency_id":"1503","name":"Sarolangun"},{"id":"1503041","regency_id":"1503","name":"Bathin VIII"},{"id":"1503050","regency_id":"1503","name":"Pauh"},{"id":"1503051","regency_id":"1503","name":"Air Hitam"},{"id":"1503060","regency_id":"1503","name":"Mandiangin"}]